libgh/__init__.py
libgh/accounts.py
libgh/common.py
libgh/libpnu2.py
libgh/main.py
libgh/organization_account.py
libgh/personal_account.py
libgh/repositories.py
pnu_libgh-0.9.5.data/data/man/man1/libgh.1.gz
pnu_libgh-0.9.5.data/data/man/man3/libgh.3.gz
pnu_libgh-0.9.5.dist-info/METADATA
pnu_libgh-0.9.5.dist-info/WHEEL
pnu_libgh-0.9.5.dist-info/entry_points.txt
pnu_libgh-0.9.5.dist-info/top_level.txt
pnu_libgh-0.9.5.dist-info/RECORD
